<?xml version="1.0" encoding="UTF-8"?>

<itemOverview>

    <overview>
        <timespan>week</timespan>
        <dateStart>2017-01-30</dateStart>
        <item>
            <ean>7614500010013</ean>
            <name>Toblerone Milk Chocolate</name>
            <unit>packet</unit>
            <description>Milk chocolate.</description>
            <categoryName>sweet-stuff</categoryName>
        </item>
        <countSold>3</countSold>
    </overview>

    <overview>
        <timespan>week</timespan>
        <dateStart>2017-02-06</dateStart>
        <item>
            <ean>7614500010013</ean>
            <name>Toblerone Milk Chocolate</name>
            <unit>packet</unit>
            <description>Milk chocolate.</description>
            <categoryName>sweet-stuff</categoryName>
        </item>
        <countSold>4</countSold>
    </overview>

</itemOverview>
